hmsm/__init__.py
hmsm/cli.py
hmsm/config.py
hmsm/debug_entry.py
hmsm/midi.py
hmsm/tmp.py
hmsm/utils.py
hmsm/data/config.json
hmsm/data/lut.npy
hmsm/discs/__init__.py
hmsm/discs/cluster.py
hmsm/discs/generator.py
hmsm/discs/utils.py
hmsm/midi/__init__.py
hmsm/midi/utils.py
hmsm/rolls/__init__.py
hmsm/rolls/analysis.py
hmsm/rolls/utils.py
hmsm/rolls/masking/__init__.py
hmsm/rolls/masking/methods.py
hmsm-0.9.1.dist-info/LICENSE
hmsm-0.9.1.dist-info/METADATA
hmsm-0.9.1.dist-info/WHEEL
hmsm-0.9.1.dist-info/entry_points.txt
hmsm-0.9.1.dist-info/top_level.txt
hmsm-0.9.1.dist-info/RECORD
