Metadata-Version: 2.1
Name: hmsm
Version: 0.9.1
Summary: Tools for image based digitization of historical music storage media
Author-email: David Fuhry <david@davidfuhry.com>
License: GPL-3.0-or-later
Project-URL: homepage, https://organology.uni-leipzig.de/
Project-URL: repository, https://github.com/digital-organology/hmsm
Classifier: Development Status :: 4 - Beta
Classifier: Environment :: Console
Classifier: Intended Audience :: Developers
Classifier: Intended Audience :: Science/Research
Classifier: License :: OSI Approved :: GNU General Public License v3 or later (GPLv3+)
Classifier: Operating System :: MacOS :: MacOS X
Classifier: Operating System :: Microsoft :: Windows
Classifier: Operating System :: POSIX :: Linux
Classifier: Programming Language :: Python
Classifier: Programming Language :: Python :: 3
Classifier: Topic :: Multimedia :: Sound/Audio :: MIDI
Classifier: Topic :: Scientific/Engineering :: Image Processing
Requires-Python: >=3.11
License-File: LICENSE
Requires-Dist: scikit-image
Requires-Dist: scikit-spatial
Requires-Dist: opencv-python
Requires-Dist: numpy
Requires-Dist: matplotlib
Requires-Dist: scikit-learn
Requires-Dist: mido
Requires-Dist: scipy
Requires-Dist: imagecodecs
Provides-Extra: midi2disc
Requires-Dist: cairosvg ; extra == 'midi2disc'
Requires-Dist: vnoise ; extra == 'midi2disc'
Provides-Extra: progressbar
Requires-Dist: enlighten ; extra == 'progressbar'
